LICENSE
README.md
pyproject.toml
setup.py
torchrecsys/__init__.py
torchrecsys.egg-info/PKG-INFO
torchrecsys.egg-info/SOURCES.txt
torchrecsys.egg-info/dependency_links.txt
torchrecsys.egg-info/requires.txt
torchrecsys.egg-info/top_level.txt
torchrecsys.egg-info/zip-safe
torchrecsys/datasets/__init__.py
torchrecsys/datasets/datasets.py
torchrecsys/datasets/utils.py
torchrecsys/external_datasets/__init__.py
torchrecsys/external_datasets/base.py
torchrecsys/external_datasets/movielens.py
torchrecsys/layers/__init__.py
torchrecsys/layers/features.py
torchrecsys/layers/inference.py
torchrecsys/models/__init__.py
torchrecsys/models/als.py
torchrecsys/models/base.py
torchrecsys/models/bert4rec.py
torchrecsys/models/bert_utils.py
torchrecsys/models/ncf.py
torchrecsys/models/utils.py
torchrecsys/task/__init__.py
torchrecsys/task/ranking.py
torchrecsys/test/__init__.py
torchrecsys/test/fixtures.py
torchrecsys/test/test_datasets.py
torchrecsys/test/test_external_datasets.py
torchrecsys/test/test_models.py